[
    {
        "name": "AL",
        "value": "26.97"
    },
    {
        "name": "AK",
        "value": "-10.60"
    },
    {
        "name": "AZ",
        "value": "22.89"
    },
    {
        "name": "AR",
        "value": "106.07"
    },
    {
        "name": "CA",
        "value": "33.92"
    },
    {
        "name": "CO",
        "value": "22.75"
    },
    {
        "name": "CT",
        "value": "75.86"
    },
    {
        "name": "DE",
        "value": "35.97"
    },
    {
        "name": "DC",
        "value": "-3.45"
    },
    {
        "name": "FL",
        "value": "19.70"
    },
    {
        "name": "GA",
        "value": "15.77"
    },
    {
        "name": "HI",
        "value": "53.10"
    },
    {
        "name": "ID",
        "value": "25.50"
    },
    {
        "name": "IL",
        "value": "59.69"
    },
    {
        "name": "IN",
        "value": "48.57"
    },
    {
        "name": "IA",
        "value": "33.20"
    },
    {
        "name": "KS",
        "value": "12.02"
    },
    {
        "name": "KY",
        "value": "50.82"
    },
    {
        "name": "LA",
        "value": "49.85"
    },
    {
        "name": "ME",
        "value": "37.98"
    },
    {
        "name": "MD",
        "value": "31.90"
    },
    {
        "name": "MA",
        "value": "15.47"
    },
    {
        "name": "MI",
        "value": "42.18"
    },
    {
        "name": "MN",
        "value": "72.01"
    },
    {
        "name": "MS",
        "value": "39.34"
    },
    {
        "name": "MO",
        "value": "40.84"
    },
    {
        "name": "MT",
        "value": "39.41"
    },
    {
        "name": "NE",
        "value": "27.77"
    },
    {
        "name": "NV",
        "value": "73.30"
    },
    {
        "name": "NH",
        "value": "109.65"
    },
    {
        "name": "NJ",
        "value": "33.67"
    },
    {
        "name": "NM",
        "value": "57.06"
    },
    {
        "name": "NY",
        "value": "19.75"
    },
    {
        "name": "NC",
        "value": "27.88"
    },
    {
        "name": "ND",
        "value": "10.82"
    },
    {
        "name": "OH",
        "value": "32.42"
    },
    {
        "name": "OK",
        "value": "58.87"
    },
    {
        "name": "OR",
        "value": "17.66"
    },
    {
        "name": "PA",
        "value": "47.04"
    },
    {
        "name": "RI",
        "value": "6.12"
    },
    {
        "name": "SC",
        "value": "51.12"
    },
    {
        "name": "SD",
        "value": "20.55"
    },
    {
        "name": "TN",
        "value": "19.28"
    },
    {
        "name": "TX",
        "value": "17.81"
    },
    {
        "name": "UT",
        "value": "44.50"
    },
    {
        "name": "VT",
        "value": "35.59"
    },
    {
        "name": "VA",
        "value": "36.48"
    },
    {
        "name": "WA",
        "value": "63.53"
    },
    {
        "name": "WV",
        "value": "57.79"
    },
    {
        "name": "WI",
        "value": "28.98"
    },
    {
        "name": "WY",
        "value": "-5.29"
    }
]